rapyd/__init__.py
rapyd/get.py
rapyd/util.py
rapyd/util/__init__.py
rapyd-0.0.3.dist-info/LICENSE
rapyd-0.0.3.dist-info/METADATA
rapyd-0.0.3.dist-info/WHEEL
rapyd-0.0.3.dist-info/top_level.txt
rapyd-0.0.3.dist-info/RECORD
