Metadata-Version: 2.1
Name: rapyd
Version: 0.0.3
Summary: Utils for generators.
Home-page: https://github.com/thorwhalen/newut/tree/master/rapyd
Author: Thor Whalen
License: mit
Platform: any
License-File: LICENSE
